heteroverlap/__init__.py
heteroverlap/source.py
heteroverlap/util.py
heteroverlap-0.0.4.dist-info/LICENSE
heteroverlap-0.0.4.dist-info/METADATA
heteroverlap-0.0.4.dist-info/WHEEL
heteroverlap-0.0.4.dist-info/top_level.txt
heteroverlap-0.0.4.dist-info/RECORD
