Metadata-Version: 2.1
Name: heteroverlap
Version: 0.0.4
Summary: Regression-based heterogeneity analysis to identify overlapping subgroup structure in high-dimensional data
Home-page: https://github.com/foliag/subgroup
Author: ZiyeLuo
Author-email: 2017100369@ruc.edu.cn
License: UNKNOWN
Platform: UNKNOWN
Classifier: Programming Language :: Python :: 3.6
Classifier: Programming Language :: Python :: 3.7
Classifier: Programming Language :: Python :: 3.8
Classifier: License :: OSI Approved :: MIT License
Classifier: Operating System :: OS Independent
License-File: LICENSE
Requires-Dist: numpy
Requires-Dist: openpyxl
Requires-Dist: pandas
Requires-Dist: scikit-learn
Requires-Dist: scipy
Requires-Dist: seaborn
